
[
    { "id": 1, "breed": "Mèo ta (Domestic Shorthair)" },
    { "id": 2, "breed": "Mèo Anh lông ngắn (British Shorthair)" },
    { "id": 3, "breed": "Mèo Anh lông dài (British Longhair)" },
    { "id": 4, "breed": "Mèo Ba Tư (Persian)" },
    { "id": 5, "breed": "Mèo Xiêm (Siamese)" },
    { "id": 6, "breed": "Mèo Maine Coon" },
    { "id": 7, "breed": "Mèo Ragdoll" },
    { "id": 8, "breed": "Mèo Sphynx" },
    { "id": 9, "breed": "Mèo Bengal" },
    { "id": 10, "breed": "Mèo Mỹ lông ngắn (American Shorthair)" },
    { "id": 11, "breed": "Mèo Nga mắt xanh (Russian Blue)" },
    { "id": 12, "breed": "Mèo Scottish Fold" },
    { "id": 13, "breed": "Mèo Miến Điện (Burmese)" },
    { "id": 14, "breed": "Mèo Birman" },
    { "id": 15, "breed": "Mèo Himalaya (Himalayan)" },
    { "id": 16, "breed": "Mèo Abyssinian" },
    { "id": 17, "breed": "Mèo Tonkinese" },
    { "id": 18, "breed": "Mèo Angora Thổ Nhĩ Kỳ (Turkish Angora)" },
    { "id": 19, "breed": "Mèo Rừng Na Uy (Norwegian Forest Cat)" },
    { "id": 20, "breed": "Mèo Savannah" },
    { "id": 21, "breed": "Mèo Ocicat" },
    { "id": 22, "breed": "Mèo Devon Rex" },
    { "id": 23, "breed": "Mèo Munchkin" },
    { "id": 24, "breed": "Mèo LaPerm" },
    { "id": 25, "breed": "Mèo Singapura" },
    { "id": 26, "breed": "Mèo Balinese" },
    { "id": 27, "breed": "Mèo Chartreux" },
    { "id": 28, "breed": "Mèo Burmilla" },
    { "id": 29, "breed": "Mèo Manx (không đuôi)" },
    { "id": 30, "breed": "Khác" }
]
